WormholeSort.py
__init__.py
WormholeSort-1.0.1.dist-info/METADATA
WormholeSort-1.0.1.dist-info/WHEEL
WormholeSort-1.0.1.dist-info/top_level.txt
WormholeSort-1.0.1.dist-info/RECORD
