Metadata-Version: 2.1
Name: WormholeSort
Version: 1.0.1
Summary: An alternative sorting method that sorts the indices rather than list elements.
Author-email: arda-guler <ardaguler09@gmail.com>
Project-URL: Homepage, https://github.com/arda-guler/WormholeSort
Project-URL: Bug Tracker, https://github.com/arda-guler/WormholeSort/issues
Classifier: Programming Language :: Python :: 3
Classifier: License :: OSI Approved :: MIT License
Classifier: Operating System :: OS Independent
Requires-Python: >=3.7
